{
  "version": "6",
  "dialect": "sqlite",
  "id": "94462ac3-4ba0-4a64-a726-5619bbba0797",
  "prevId": "00000000-0000-0000-0000-000000000000",
  "tables": {
    "channel": {
      "name": "channel",
      "columns": {
        "id": {
          "name": "id",
          "type": "text(255)",
          "primaryKey": true,
          "notNull": true,
          "autoincrement": false
        },
        "name": {
          "name": "name",
          "type": "text(255)",
          "primaryKey": false,
          "notNull": true,
          "autoincrement": false
        },
        "description": {
          "name": "description",
          "type": "text",
          "primaryKey": false,
          "notNull": false,
          "autoincrement": false
        },
        "image_url": {
          "name": "image_url",
          "type": "text",
          "primaryKey": false,
          "notNull": false,
          "autoincrement": false
        },
        "created_at": {
          "name": "created_at",
          "type": "integer",
          "primaryKey": false,
          "notNull": true,
          "autoincrement": false,
          "default": "(unixepoch())"
        }
      },
      "indexes": {},
      "foreignKeys": {},
      "compositePrimaryKeys": {},
      "uniqueConstraints": {},
      "checkConstraints": {}
    },
    "video": {
      "name": "video",
      "columns": {
        "id": {
          "name": "id",
          "type": "text(255)",
          "primaryKey": true,
          "notNull": true,
          "autoincrement": false
        },
        "title": {
          "name": "title",
          "type": "text(255)",
          "primaryKey": false,
          "notNull": true,
          "autoincrement": false
        },
        "description": {
          "name": "description",
          "type": "text",
          "primaryKey": false,
          "notNull": true,
          "autoincrement": false
        },
        "summary": {
          "name": "summary",
          "type": "text",
          "primaryKey": false,
          "notNull": true,
          "autoincrement": false
        },
        "video_id": {
          "name": "video_id",
          "type": "text(255)",
          "primaryKey": false,
          "notNull": true,
          "autoincrement": false
        },
        "channel_name": {
          "name": "channel_name",
          "type": "text(255)",
          "primaryKey": false,
          "notNull": true,
          "autoincrement": false
        },
        "channel_id": {
          "name": "channel_id",
          "type": "text(255)",
          "primaryKey": false,
          "notNull": true,
          "autoincrement": false
        },
        "created_at": {
          "name": "created_at",
          "type": "integer",
          "primaryKey": false,
          "notNull": true,
          "autoincrement": false,
          "default": "(unixepoch())"
        },
        "duration": {
          "name": "duration",
          "type": "integer",
          "primaryKey": false,
          "notNull": true,
          "autoincrement": false
        },
        "time_to_generate_summary": {
          "name": "time_to_generate_summary",
          "type": "integer",
          "primaryKey": false,
          "notNull": true,
          "autoincrement": false
        },
        "video_published_at": {
          "name": "video_published_at",
          "type": "integer",
          "primaryKey": false,
          "notNull": true,
          "autoincrement": false,
          "default": "(unixepoch())"
        },
        "thumbnail_url": {
          "name": "thumbnail_url",
          "type": "text",
          "primaryKey": false,
          "notNull": true,
          "autoincrement": false
        }
      },
      "indexes": {},
      "foreignKeys": {
        "video_channel_id_channel_id_fk": {
          "name": "video_channel_id_channel_id_fk",
          "tableFrom": "video",
          "tableTo": "channel",
          "columnsFrom": [
            "channel_id"
          ],
          "columnsTo": [
            "id"
          ],
          "onDelete": "cascade",
          "onUpdate": "no action"
        }
      },
      "compositePrimaryKeys": {},
      "uniqueConstraints": {},
      "checkConstraints": {}
    }
  },
  "views": {},
  "enums": {},
  "_meta": {
    "schemas": {},
    "tables": {},
    "columns": {}
  },
  "internal": {
    "indexes": {}
  }
}